{
  "_fv": 13,
  "_type": "tool",
  "definition": {
    "renderType": 0,
    "texture": "silver_axe",
    "customModelName": "Normal",
    "name": "Silver Axe",
    "specialInfo": [],
    "creativeTab": {
      "value": "TOOLS"
    },
    "toolType": "Axe",
    "harvestLevel": 2,
    "efficiency": 6.0,
    "attackSpeed": 1.0,
    "enchantability": 14,
    "damageVsEntity": 2.0,
    "usageCount": 250,
    "blocksAffected": [],
    "hasGlow": false,
    "repairItems": [
      {
        "value": "CUSTOM:SilverIngot"
      }
    ],
    "stayInGridWhenCrafting": false,
    "damageOnCrafting": false
  }
}